sherpa_ai/__init__.py
sherpa_ai/actions/__init__.py
sherpa_ai/actions/arxiv_search.py
sherpa_ai/actions/base.py
sherpa_ai/actions/belief_actions.py
sherpa_ai/actions/chain_actions.py
sherpa_ai/actions/context_search.py
sherpa_ai/actions/deliberation.py
sherpa_ai/actions/dynamic.py
sherpa_ai/actions/empty.py
sherpa_ai/actions/entity_validation.py
sherpa_ai/actions/exceptions.py
sherpa_ai/actions/google_search.py
sherpa_ai/actions/link_scraper.py
sherpa_ai/actions/mock.py
sherpa_ai/actions/number_validation.py
sherpa_ai/actions/planning.py
sherpa_ai/actions/sherpa_mcp_adapter.py
sherpa_ai/actions/synthesize.py
sherpa_ai/actions/utils/__init__.py
sherpa_ai/actions/utils/refinement.py
sherpa_ai/actions/utils/reranking.py
sherpa_ai/agents/__init__.py
sherpa_ai/agents/agent_pool.py
sherpa_ai/agents/base.py
sherpa_ai/agents/ml_engineer.py
sherpa_ai/agents/physicist.py
sherpa_ai/agents/qa_agent.py
sherpa_ai/agents/user.py
sherpa_ai/config/__init__.py
sherpa_ai/config/task_config.py
sherpa_ai/config/task_result.py
sherpa_ai/connectors/base.py
sherpa_ai/connectors/chroma_vector_store.py
sherpa_ai/connectors/scripts/load_dump_to_chroma.py
sherpa_ai/connectors/scripts/query_chroma.py
sherpa_ai/connectors/vectorstores.py
sherpa_ai/cost_tracking/backup.py
sherpa_ai/cost_tracking/cli.py
sherpa_ai/cost_tracking/logger.py
sherpa_ai/cost_tracking/pricing.py
sherpa_ai/cost_tracking/reporting.py
sherpa_ai/database/__init__.py
sherpa_ai/database/user_usage_tracker.py
sherpa_ai/error_handling/__init__.py
sherpa_ai/error_handling/agent_error_handler.py
sherpa_ai/events.py
sherpa_ai/memory/__init__.py
sherpa_ai/memory/belief.py
sherpa_ai/memory/shared_memory.py
sherpa_ai/memory/shared_memory_with_vectordb.py
sherpa_ai/memory/state_machine.py
sherpa_ai/memory/utils.py
sherpa_ai/models/__init__.py
sherpa_ai/models/chat_model_with_logging.py
sherpa_ai/models/sherpa_base_chat_model.py
sherpa_ai/models/sherpa_base_model.py
sherpa_ai/output_parsers/__init__.py
sherpa_ai/output_parsers/base.py
sherpa_ai-0.5.0.dist-info/METADATA
sherpa_ai-0.5.0.dist-info/WHEEL
sherpa_ai-0.5.0.dist-info/RECORD
