Metadata-Version: 2.4
Name: sherpa-ai
Version: 0.5.0
Summary: Sherpa: AI-augmented thinking companion
Requires-Python: >=3.10,<3.14
Classifier: Programming Language :: Python :: 3
Classifier: Programming Language :: Python :: 3.10
Classifier: Programming Language :: Python :: 3.11
Classifier: Programming Language :: Python :: 3.12
Classifier: Programming Language :: Python :: 3.13
Requires-Dist: hydra-core (>=1.3.2,<2.0.0)
Requires-Dist: importlib (>=1.0.4,<2.0.0)
Requires-Dist: langchain-community (>=0.3.13,<0.4)
Requires-Dist: langchain-core (>=0.3.28,<0.4)
Requires-Dist: langchain-openai (>=0.2.14,<0.3)
Requires-Dist: loguru (>=0.7.0,<0.8.0)
Requires-Dist: mcp (>=1.12.4,<2.0.0)
Requires-Dist: pydantic (>=2.5.3,<3.0.0)
Requires-Dist: pydash (>=8.0.3,<9.0.0)
Requires-Dist: pykka (>=4.2.0,<5.0.0)
Requires-Dist: python-dotenv (>=1.0.0,<2.0.0)
Requires-Dist: spacy (==3.8.7)
Requires-Dist: tiktoken (>=0.6.0,<1.0)
Requires-Dist: transitions (>=0.9.2,<0.10.0)
Requires-Dist: unstructured (>=0.10.11,<0.11.0)
Project-URL: Repository, https://github.com/Aggregate-Intellect/sherpa
